jetstreamext/__init__.py
jetstreamext/_version.py
jetstreamext/getbatch.py
jetstreamext/py.typed
jetstreamext-0.4.0.dist-info/licenses/NOTICE
jetstreamext-0.4.0.dist-info/WHEEL
jetstreamext-0.4.0.dist-info/METADATA
jetstreamext-0.4.0.dist-info/RECORD
