Metadata-Version: 2.4
Name: jetstreamext
Version: 0.4.0
Summary: JetStream Extensions is a set of utilities providing additional features to `jetstream` package in nats-py client.
Author: Oliver Lambson
Author-email: Oliver Lambson <oliverlambson@gmail.com>
License-Expression: Apache-2.0
License-File: NOTICE
Classifier: License :: OSI Approved :: Apache Software License
Classifier: Intended Audience :: Developers
Classifier: Development Status :: 2 - Pre-Alpha
Classifier: Programming Language :: Python
Classifier: Programming Language :: Python :: 3
Classifier: Programming Language :: Python :: 3.10
Classifier: Programming Language :: Python :: 3.11
Classifier: Programming Language :: Python :: 3.12
Classifier: Programming Language :: Python :: 3.13
Requires-Dist: natsext>=0.1.0
Requires-Dist: nats-py>=2.11.0
Requires-Python: >=3.10
Project-URL: Bug Tracker, https://github.com/oliverlambson/orbit.py/issues
Project-URL: Homepage, https://github.com/oliverlambson/orbit.py
